LICENSE
README.rst
setup.cfg
setup.py
src/markdown_mermaid_to_images/__init__.py
src/markdown_mermaid_to_images/cli.py
src/markdown_mermaid_to_images.egg-info/PKG-INFO
src/markdown_mermaid_to_images.egg-info/SOURCES.txt
src/markdown_mermaid_to_images.egg-info/dependency_links.txt
src/markdown_mermaid_to_images.egg-info/entry_points.txt
src/markdown_mermaid_to_images.egg-info/not-zip-safe
src/markdown_mermaid_to_images.egg-info/requires.txt
src/markdown_mermaid_to_images.egg-info/top_level.txt