Metadata-Version: 2.1
Name: markdown-mermaid-to-images
Version: 0.3.0.post1
Summary: Exports mermaid diagrams in Markdown documents as images.
Home-page: https://gitlab.com/hmajid2301/markdown-mermaid-to-images.git
Author: hmajid2301
Author-email: hmajid2301@gmail.com
License: Apache License
Keywords: markdown,mermaid,exporter
Platform: UNKNOWN
Classifier: Programming Language :: Python
Classifier: Intended Audience :: Developers
Classifier: Operating System :: OS Independent
Classifier: Topic :: Software Development :: Libraries :: Python Modules
Requires-Python: ~=3.6
License-File: LICENSE
